duplexanalysis/fsd.py
duplexanalysis/fsd_beforevsafter.py
duplexanalysis/fsd_regions.py
duplexanalysis/hd.py
duplexanalysis-0.0.3.dist-info/DESCRIPTION.rst
duplexanalysis-0.0.3.dist-info/METADATA
duplexanalysis-0.0.3.dist-info/RECORD
duplexanalysis-0.0.3.dist-info/WHEEL
duplexanalysis-0.0.3.dist-info/metadata.json
duplexanalysis-0.0.3.dist-info/top_level.txt
