Metadata-Version: 2.0
Name: duplexanalysis
Version: 0.0.3
Summary: Tool for analysing duplex sequencing data
Home-page: https://github.com/monikaheinzl/duplexanalysis
Author: Monika Heinzl
Author-email: monika.heinzl@edumail.at
License: UNKNOWN
Platform: UNKNOWN
